setup.cfg
setup.py
create2/__init__.py
create2/create2.py
create2/create2emulator.py
create2/opcode.py
create2/sample.py
create2/sample2.py
create2/sci.py
create2/sensor.py
create2/sensor_observer.py
libcreate2py.egg-info/PKG-INFO
libcreate2py.egg-info/SOURCES.txt
libcreate2py.egg-info/dependency_links.txt
libcreate2py.egg-info/requires.txt
libcreate2py.egg-info/top_level.txt
libcreate2py.egg-info/zip-safe